{
  "web-methods": {
    "*": {
      "*": {
        "siteOwner": { "invoke": true },
        "siteMember": { "invoke": false },
        "anonymous": { "invoke": false }
      }
    },
    "backend/contact.jsw": {
      "sendContactEmail": {
        "siteOwner": { "invoke": true },
        "siteMember": { "invoke": true },
        "anonymous": { "invoke": true }
      }
    },
    "backend/members.jsw": {
      "createMember": {
        "siteOwner": { "invoke": true },
        "siteMember": { "invoke": false },
        "anonymous": { "invoke": true }
      }
    },
    "backend/orders.jsw": {
      "getMemberOrders": {
        "siteOwner": { "invoke": true },
        "siteMember": { "invoke": true },
        "anonymous": { "invoke": false }
      }
    }
  }
}
